pysound/__init__.py
pysound/buffer.py
pysound/const.py
pysound/effects.py
pysound/envelopes.py
pysound/mixers.py
pysound/oscillators.py
pysound/sequencers.py
pysound/soundfile.py
pysound-0.0.dist-info/METADATA
pysound-0.0.dist-info/RECORD
pysound-0.0.dist-info/WHEEL
pysound-0.0.dist-info/top_level.txt
